[
  {
    "email": "john@sg-logistics-services.com",
    "name": "John BizDirector",
    "company": "SG Logistics Services",
    "subject": "AI Agent Transformation for SG Logistics Services",
    "body": "Hi John,\n\nI noticed SG Logistics Services is doing great work. At AIMS, we help Singapore SMEs transition into autonomous, high-efficiency AI agents. I would love to schedule a quick chat to explore how this applies to you.\n\nBest,\nLily"
  },
  {
    "email": "karen.paek@viki.com",
    "name": "Karen Paek",
    "company": "Viki",
    "subject": "AI Agent Transformation for Viki",
    "body": "Hi Karen,\n\nI noticed Viki is doing great work. At AIMS, we help Singapore SMEs transition into autonomous, high-efficiency AI agents. I would love to schedule a quick chat to explore how this applies to you.\n\nBest,\nLily"
  }
]